gratin/__init__.py
gratin/standard.py
gratin/data/__init__.py
gratin/data/data.py
gratin/data/data_tools.py
gratin/data/datamodule.py
gratin/data/dataset.py
gratin/data/rep_dataset.py
gratin/data/skeleton_data.py
gratin/layers/InvNet.py
gratin/layers/__init__.py
gratin/layers/diverse.py
gratin/layers/encoders.py
gratin/layers/fBMGenerator.py
gratin/layers/features_init.py
gratin/layers/minimal_conv.py
gratin/layers/mmd_pytorch.py
gratin/models/BFlowDiffusion.py
gratin/models/BFlow_old.py
gratin/models/MMD_net.py
gratin/models/SelfSup.py
gratin/models/__init__.py
gratin/models/main_net.py
gratin/models/main_net_versatile.py
gratin/models/utils.py
gratin/models/__pycache__/BFlow.cpython-38.pyc.140382539799328
gratin/simulation/__init__.py
gratin/simulation/diffusion_models.py
gratin/simulation/traj_tools.py
gratin/simulation/utils_andi.py
gratin/training/__init__.py
gratin/training/callbacks.py
gratin/training/network_tools.py
gratin/training/utils.py
gratin-0.1.11.dist-info/AUTHORS.rst
gratin-0.1.11.dist-info/LICENSE.txt
gratin-0.1.11.dist-info/METADATA
gratin-0.1.11.dist-info/WHEEL
gratin-0.1.11.dist-info/top_level.txt
gratin-0.1.11.dist-info/RECORD
