Metadata-Version: 2.1
Name: gratin
Version: 0.1.11
Summary: Random walk analysis tool using graph neural networks
Home-page: https://github.com/hippover/gratin/
Author: Hippolyte Verdier
Author-email: hverdier@pasteur.fr
License: mit
Project-URL: Documentation, https://gratin.readthedocs.io/en/latest/
Platform: any
Classifier: Development Status :: 4 - Beta
Classifier: Programming Language :: Python
Requires-Python: >=3.8
License-File: LICENSE.txt
License-File: AUTHORS.rst
Requires-Dist: setuptools (==59.5.0)
Requires-Dist: sphinx (>=3.2.1)
Requires-Dist: torch (>=2.0)
Requires-Dist: torchmetrics (>=0.11)
Requires-Dist: pytorch-lightning (>=2.0)
Requires-Dist: keras
Requires-Dist: tqdm
Requires-Dist: matplotlib
Requires-Dist: numpy
Requires-Dist: fbm
Requires-Dist: scipy
Requires-Dist: pandas
Requires-Dist: umap-learn[parametric_umap] (>=0.5.2) ; platform_system != "Darwin"
Requires-Dist: tensorflow (>=2.12) ; platform_system == "Linux"
Requires-Dist: importlib-metadata ; python_version < "3.8"
Provides-Extra: testing
Requires-Dist: pytest ; extra == 'testing'
Requires-Dist: pytest-cov ; extra == 'testing'
